LICENSE.txt
MANIFEST.in
README.md
RELEASES_NOTES.md
requirements.txt
setup.cfg
setup.py
anacore/STARLog.py
anacore/__init__.py
anacore/abstractFile.py
anacore/annotVcf.py
anacore/bed.py
anacore/filters.py
anacore/fusion.py
anacore/genomicRegion.py
anacore/getterPath.py
anacore/gff.py
anacore/gtf.py
anacore/hgvs.py
anacore/maf.py
anacore/matrix.py
anacore/node.py
anacore/picardIO.py
anacore/region.py
anacore/sequence.py
anacore/sequenceIO.py
anacore/sv.py
anacore/tophatFusion.py
anacore/vcf.py
anacore/wig.py
anacore.egg-info/PKG-INFO
anacore.egg-info/SOURCES.txt
anacore.egg-info/dependency_links.txt
anacore.egg-info/requires.txt
anacore.egg-info/top_level.txt
anacore/db/__init__.py
anacore/db/homo_sapiens/__init__.py
anacore/db/homo_sapiens/accession.py
anacore/illumina/__init__.py
anacore/illumina/base.py
anacore/illumina/run.py
anacore/illumina/samplesheet.py
anacore/illumina/demultiplex/__init__.py
anacore/illumina/demultiplex/base.py
anacore/illumina/demultiplex/bcl2fastq.py
anacore/illumina/demultiplex/bclconvert.py
anacore/msi/__init__.py
anacore/msi/annot.py
anacore/msi/base.py
anacore/msi/hubble.py
anacore/msi/locus.py
anacore/msi/msings.py
anacore/msi/msisensorpro.py
anacore/msi/reportIO.py
anacore/msi/sample.py
test/test_abstractFile.py
test/test_bed.py
test/test_filters.py
test/test_fusion.py
test/test_genomicRegion.py
test/test_getterPath.py
test/test_gff.py
test/test_gtf.py
test/test_hgvs.py
test/test_picardIO.py
test/test_region.py
test/test_sequence.py
test/test_sequenceIO.py
test/test_sv.py
test/test_vcf.py
test/test_wig.py