Metadata-Version: 1.2
Name: anacore
Version: 3.1.0
Summary: Libraries for managing standard file formats and objects from NGS.
Home-page: https://github.com/bialimed/anacore
Author: Frederic Escudie
Author-email: escudie.frederic@iuct-oncopole.fr
License: GNU GPL v3
Keywords: bio NGS
Platform: UNKNOWN
Requires-Python: >=3.8
